__init__.py
store/__init__.py
store/main.py
storethisstuff-0.4.dist-info/METADATA
storethisstuff-0.4.dist-info/WHEEL
storethisstuff-0.4.dist-info/top_level.txt
storethisstuff-0.4.dist-info/RECORD
